winui3/Microsoft.WindowsAppRuntime.Bootstrap.dll
winui3/_winui3_microsoft_windows_applicationmodel_dynamicdependency_bootstrap.cp310-win_amd64.pyd
winui3/_winui3_microsoft_windows_applicationmodel_dynamicdependency_bootstrap.pyi
winui3/microsoft/windows/applicationmodel/dynamicdependency/bootstrap/__init__.py
winui3/microsoft/windows/applicationmodel/dynamicdependency/bootstrap/py.typed
wasdk_microsoft_windows_applicationmodel_dynamicdependency_bootstrap-1.8.260101001.dist-info/METADATA
wasdk_microsoft_windows_applicationmodel_dynamicdependency_bootstrap-1.8.260101001.dist-info/WHEEL
wasdk_microsoft_windows_applicationmodel_dynamicdependency_bootstrap-1.8.260101001.dist-info/top_level.txt
wasdk_microsoft_windows_applicationmodel_dynamicdependency_bootstrap-1.8.260101001.dist-info/RECORD
